{
    "success": true,
    "timestamp": 1701336903,
    "base": "EUR",
    "date": "2023-11-30",
    "rates": {
        "AED": 4.015787,
        "AFN": 76.545903,
        "ALL": 102.037942,
        "AMD": 440.538619,
        "ANG": 1.973664,
        "AOA": 907.610122,
        "ARS": 393.635846,
        "AUD": 1.651839,
        "AWG": 1.971044,
        "AZN": 1.861637,
        "BAM": 1.949837,
        "BBD": 2.211138,
        "BDT": 120.740744,
        "BGN": 1.955063,
        "BHD": 0.412168,
        "BIF": 3114.432544,
        "BMD": 1.093506,
        "BND": 1.458819,
        "BOB": 7.56679,
        "BRL": 5.364749,
        "BSD": 1.095151,
        "BTC": 2.9211465e-05,
        "BTN": 91.193189,
        "BWP": 14.718986,
        "BYN": 3.607369,
        "BYR": 21432.713264,
        "BZD": 2.207449,
        "CAD": 1.487507,
        "CDF": 2914.193603,
        "CHF": 0.95655,
        "CLF": 0.03444,
        "CLP": 950.311301,
        "CNY": 7.746777,
        "COP": 4363.744161,
        "CRC": 580.112604,
        "CUC": 1.093506,
        "CUP": 28.977903,
        "CVE": 109.925302,
        "CZK": 24.313172,
        "DJF": 194.98369,
        "DKK": 7.455216,
        "DOP": 62.16605,
        "DZD": 147.039365,
        "EGP": 33.793788,
        "ERN": 16.402587,
        "ETB": 60.981104,
        "EUR": 1,
        "FJD": 2.437101,
        "FKP": 0.861906,
        "GBP": 0.863175,
        "GEL": 2.957934,
        "GGP": 0.861906,
        "GHS": 13.132936,
        "GIP": 0.861906,
        "GMD": 73.620267,
        "GNF": 9412.347186,
        "GTQ": 8.569518,
        "GYD": 229.117206,
        "HKD": 8.539351,
        "HNL": 27.024353,
        "HRK": 7.699997,
        "HTG": 145.064366,
        "HUF": 378.844533,
        "IDR": 16968.202546,
        "ILS": 4.044287,
        "IMP": 0.861906,
        "INR": 91.165029,
        "IQD": 1432.49257,
        "IRR": 46200.619493,
        "ISK": 150.499296,
        "JEP": 0.861906,
        "JMD": 170.448724,
        "JOD": 0.775732,
        "JPY": 161.007656,
        "KES": 167.506774,
        "KGS": 97.36269,
        "KHR": 4506.157203,
        "KMF": 490.574033,
        "KPW": 984.207633,
        "KRW": 1417.489522,
        "KWD": 0.337445,
        "KYD": 0.912592,
        "KZT": 502.972582,
        "LAK": 22642.752653,
        "LBP": 16438.12585,
        "LKR": 360.746148,
        "LRD": 205.634105,
        "LSL": 20.459157,
        "LTL": 3.228839,
        "LVL": 0.661451,
        "LYD": 5.25936,
        "MAD": 10.978251,
        "MDL": 19.515317,
        "MGA": 4971.794975,
        "MKD": 61.376219,
        "MMK": 2299.766723,
        "MNT": 3782.910743,
        "MOP": 8.801283,
        "MRO": 390.381375,
        "MUR": 48.256646,
        "MVR": 16.785675,
        "MWK": 1840.37011,
        "MXN": 19.07512,
        "MYR": 5.095193,
        "MZN": 69.164186,
        "NAD": 20.459957,
        "NGN": 863.314057,
        "NIO": 40.077433,
        "NOK": 11.692387,
        "NPR": 145.910433,
        "NZD": 1.775159,
        "OMR": 0.42099,
        "PAB": 1.095121,
        "PEN": 4.072545,
        "PGK": 4.083512,
        "PHP": 60.635413,
        "PKR": 312.65841,
        "PLN": 4.349283,
        "PYG": 8138.111567,
        "QAR": 3.980905,
        "RON": 4.972264,
        "RSD": 116.843662,
        "RUB": 96.731618,
        "RWF": 1361.414695,
        "SAR": 4.10239,
        "SBD": 9.267664,
        "SCR": 14.291493,
        "SDG": 657.196987,
        "SEK": 11.404204,
        "SGD": 1.459694,
        "SHP": 1.330523,
        "SLE": 24.730479,
        "SLL": 21596.738793,
        "SOS": 624.942005,
        "SRD": 41.333971,
        "STD": 22633.361841,
        "SYP": 14218.0052,
        "SZL": 20.460017,
        "THB": 38.426922,
        "TJS": 11.974795,
        "TMT": 3.82727,
        "TND": 3.382762,
        "TOP": 2.578597,
        "TRY": 31.550999,
        "TTD": 7.429144,
        "TWD": 34.237118,
        "TZS": 2739.232076,
        "UAH": 39.847935,
        "UGX": 4178.183833,
        "USD": 1.093506,
        "UYU": 42.94826,
        "UZS": 13467.811976,
        "VEF": 3874108.049803,
        "VES": 38.764296,
        "VND": 26547.586544,
        "VUV": 130.976679,
        "WST": 2.996493,
        "XAF": 653.957032,
        "XAG": 0.043709,
        "XAU": 0.000536,
        "XCD": 2.955254,
        "XDR": 0.822883,
        "XOF": 653.957032,
        "XPF": 119.409915,
        "YER": 273.759299,
        "ZAR": 20.600123,
        "ZMK": 9842.861996,
        "ZMW": 26.009456,
        "ZWL": 352.108415
    }
}