{
    "success": true,
    "timestamp": 1701342003,
    "base": "EUR",
    "date": "2023-11-30",
    "rates": {
        "AED": 4.009435,
        "AFN": 76.428917,
        "ALL": 101.881996,
        "AMD": 439.865339,
        "ANG": 1.970648,
        "AOA": 906.22275,
        "ARS": 393.024188,
        "AUD": 1.653794,
        "AWG": 1.968032,
        "AZN": 1.862915,
        "BAM": 1.946857,
        "BBD": 2.207758,
        "BDT": 120.556214,
        "BGN": 1.954597,
        "BHD": 0.411566,
        "BIF": 3109.672716,
        "BMD": 1.091835,
        "BND": 1.456589,
        "BOB": 7.555225,
        "BRL": 5.356429,
        "BSD": 1.093477,
        "BTC": 2.9174124e-05,
        "BTN": 91.053817,
        "BWP": 14.69649,
        "BYN": 3.601856,
        "BYR": 21399.957367,
        "BZD": 2.204075,
        "CAD": 1.485627,
        "CDF": 2909.739403,
        "CHF": 0.95565,
        "CLF": 0.034388,
        "CLP": 948.858865,
        "CNY": 7.74176,
        "COP": 4357.074993,
        "CRC": 579.22601,
        "CUC": 1.091835,
        "CUP": 28.933616,
        "CVE": 109.757302,
        "CZK": 24.31461,
        "DJF": 194.685694,
        "DKK": 7.454741,
        "DOP": 62.071084,
        "DZD": 146.644231,
        "EGP": 33.735833,
        "ERN": 16.377518,
        "ETB": 60.887906,
        "EUR": 1,
        "FJD": 2.436702,
        "FKP": 0.860589,
        "GBP": 0.863531,
        "GEL": 2.953451,
        "GGP": 0.860589,
        "GHS": 13.112667,
        "GIP": 0.860589,
        "GMD": 73.507767,
        "GNF": 9397.970574,
        "GTQ": 8.556421,
        "GYD": 228.767043,
        "HKD": 8.527539,
        "HNL": 26.983051,
        "HRK": 7.688229,
        "HTG": 144.842662,
        "HUF": 379.930033,
        "IDR": 16973.27792,
        "ILS": 4.046208,
        "IMP": 0.860589,
        "INR": 91.025201,
        "IQD": 1430.303273,
        "IRR": 46130.009969,
        "ISK": 150.49886,
        "JEP": 0.860589,
        "JMD": 170.188225,
        "JOD": 0.774551,
        "JPY": 161.124234,
        "KES": 167.323533,
        "KGS": 97.352661,
        "KHR": 4499.270383,
        "KMF": 489.824228,
        "KPW": 982.703456,
        "KRW": 1418.850046,
        "KWD": 0.337046,
        "KYD": 0.911198,
        "KZT": 502.203882,
        "LAK": 22608.147437,
        "LBP": 16413.002832,
        "LKR": 360.194815,
        "LRD": 205.319101,
        "LSL": 20.427972,
        "LTL": 3.223903,
        "LVL": 0.660439,
        "LYD": 5.251822,
        "MAD": 10.961471,
        "MDL": 19.485492,
        "MGA": 4964.196516,
        "MKD": 61.282417,
        "MMK": 2296.25196,
        "MNT": 3777.129271,
        "MOP": 8.787832,
        "MRO": 389.78475,
        "MUR": 48.156011,
        "MVR": 16.759582,
        "MWK": 1837.557889,
        "MXN": 19.059612,
        "MYR": 5.0874,
        "MZN": 69.058482,
        "NAD": 20.428064,
        "NGN": 862.004419,
        "NIO": 40.016182,
        "NOK": 11.68002,
        "NPR": 145.687436,
        "NZD": 1.776311,
        "OMR": 0.420324,
        "PAB": 1.093447,
        "PEN": 4.066321,
        "PGK": 4.077271,
        "PHP": 60.588631,
        "PKR": 312.18057,
        "PLN": 4.354438,
        "PYG": 8125.673984,
        "QAR": 3.974825,
        "RON": 4.972649,
        "RSD": 116.665088,
        "RUB": 96.830987,
        "RWF": 1359.334027,
        "SAR": 4.096024,
        "SBD": 9.2535,
        "SCR": 14.234584,
        "SDG": 656.192957,
        "SEK": 11.409742,
        "SGD": 1.459504,
        "SHP": 1.32849,
        "SLE": 24.692683,
        "SLL": 21563.732627,
        "SOS": 623.986536,
        "SRD": 41.2708,
        "STD": 22598.770977,
        "SYP": 14196.275636,
        "SZL": 20.428231,
        "THB": 38.485025,
        "TJS": 11.956493,
        "TMT": 3.821421,
        "TND": 3.377594,
        "TOP": 2.574653,
        "TRY": 31.50208,
        "TTD": 7.41779,
        "TWD": 34.221914,
        "TZS": 2745.963678,
        "UAH": 39.787035,
        "UGX": 4171.79826,
        "USD": 1.091835,
        "UYU": 42.882622,
        "UZS": 13447.228942,
        "VEF": 3868187.199632,
        "VES": 38.705052,
        "VND": 26487.906414,
        "VUV": 130.776506,
        "WST": 2.991913,
        "XAF": 652.95758,
        "XAG": 0.043691,
        "XAU": 0.000536,
        "XCD": 2.950738,
        "XDR": 0.821626,
        "XOF": 652.95758,
        "XPF": 119.19583,
        "YER": 273.340533,
        "ZAR": 20.590794,
        "ZMK": 9827.823232,
        "ZMW": 25.969706,
        "ZWL": 351.570283
    }
}